daemon_metrics.py
daemon_metrics-1.0.1.dist-info/METADATA
daemon_metrics-1.0.1.dist-info/WHEEL
daemon_metrics-1.0.1.dist-info/RECORD
