Metadata-Version: 2.3
Name: daemon-metrics
Version: 1.0.1
Summary: 
License: GPL
Author: François Schmidts
Author-email: francois@schmidts.fr
Requires-Python: >=3.9
Classifier: License :: Other/Proprietary License
Classifier: Programming Language :: Python :: 3
Classifier: Programming Language :: Python :: 3.9
Classifier: Programming Language :: Python :: 3.10
Classifier: Programming Language :: Python :: 3.11
Classifier: Programming Language :: Python :: 3.12
Classifier: Programming Language :: Python :: 3.13
Requires-Dist: prometheus-client (>=0.22.1)
